hakeem/__init__.py
hakeem/aggregation/__init__.py
hakeem/aggregation/aggregators/__init__.py
hakeem/aggregation/aggregators/condorcet.py
hakeem/aggregation/aggregators/mallows.py
hakeem/aggregation/base.py
hakeem/utils/__init__.py
hakeem/utils/coerce.py
hakeem/utils/inventory.py
hakeem-1.0.1.dist-info/METADATA
hakeem-1.0.1.dist-info/WHEEL
hakeem-1.0.1.dist-info/RECORD
