Metadata-Version: 2.1
Name: hakeem
Version: 1.0.1
Summary: Minimalistic collective data labeling tools
Author: Tahar Allouche
Author-email: tahar.allouche.pro@gmail.com
Requires-Python: >=3.9,<4.0
Classifier: Programming Language :: Python :: 3
Classifier: Programming Language :: Python :: 3.9
Classifier: Programming Language :: Python :: 3.10
Classifier: Programming Language :: Python :: 3.11
Classifier: Programming Language :: Python :: 3.12
Classifier: Programming Language :: Python :: 3.13
Requires-Dist: pandas (>=2.2.3,<3.0.0)
